hoax/__init__.py
hoax/drivers.py
hoax/hoa.py
hoax/main.py
hoax/runners.py
hoax/util.py
hoax/config/__init__.py
hoax/config/config.py
hoax/config/toml_v1.py
hoax_hoa_executor-0.1.6.dist-info/METADATA
hoax_hoa_executor-0.1.6.dist-info/WHEEL
hoax_hoa_executor-0.1.6.dist-info/entry_points.txt
hoax_hoa_executor-0.1.6.dist-info/licenses/LICENSE
hoax_hoa_executor-0.1.6.dist-info/RECORD
