Metadata-Version: 2.4
Name: hoax-hoa-executor
Version: 0.1.6
Summary: Execute HOA omega-automata
Project-URL: Repository, https://github.com/lou1306/hoax
Project-URL: Issues, https://github.com/lou1306/hoax/issues
Author-email: Luca Di Stefano <luca.di.stefano@tuwien.ac.at>
License-Expression: MIT
License-File: LICENSE
Requires-Python: <3.15,>=3.12
Requires-Dist: hoa-utils-redux
Requires-Dist: msgpack>=1.1.0
Requires-Dist: msgspec<1,>=0.20.0
Requires-Dist: networkit
Requires-Dist: tomli<3,>=2.0.1
Requires-Dist: typer>=0.21.1
